{
 "custom_fields": [
  {
   "_assign": null,
   "_comments": null,
   "_liked_by": null,
   "_user_tags": null,
   "allow_in_quick_entry": 0,
   "allow_on_submit": 0,
   "bold": 0,
   "collapsible": 0,
   "collapsible_depends_on": null,
   "columns": 0,
   "creation": "2022-05-11 14:22:22.361837",
   "default": null,
   "depends_on": null,
   "description": null,
   "docstatus": 0,
   "dt": "Delivery Note",
   "fetch_from": null,
   "fetch_if_empty": 0,
   "fieldname": "informations_fiscales",
   "fieldtype": "Section Break",
   "hidden": 0,
   "hide_border": 0,
   "hide_days": 0,
   "hide_seconds": 0,
   "idx": 16,
   "ignore_user_permissions": 0,
   "ignore_xss_filter": 0,
   "in_global_search": 0,
   "in_list_view": 0,
   "in_preview": 0,
   "in_standard_filter": 0,
   "insert_after": "return_against",
   "is_system_generated": 0,
   "is_virtual": 0,
   "label": "Informations Fiscales",
   "length": 0,
   "mandatory_depends_on": null,
   "modified": "2022-05-11 14:22:22.361837",
   "modified_by": "Administrator",
   "module": null,
   "name": "Delivery Note-informations_fiscales",
   "no_copy": 0,
   "non_negative": 0,
   "options": null,
   "owner": "Administrator",
   "permlevel": 0,
   "precision": "",
   "print_hide": 0,
   "print_hide_if_no_value": 0,
   "print_width": null,
   "read_only": 0,
   "read_only_depends_on": null,
   "report_hide": 0,
   "reqd": 0,
   "search_index": 0,
   "translatable": 0,
   "unique": 0,
   "width": null
  },
  {
   "_assign": null,
   "_comments": null,
   "_liked_by": null,
   "_user_tags": null,
   "allow_in_quick_entry": 0,
   "allow_on_submit": 0,
   "bold": 0,
   "collapsible": 0,
   "collapsible_depends_on": null,
   "columns": 0,
   "creation": "2022-05-11 14:22:23.098397",
   "default": null,
   "depends_on": null,
   "description": null,
   "docstatus": 0,
   "dt": "Delivery Note",
   "fetch_from": "customer.rc",
   "fetch_if_empty": 0,
   "fieldname": "rc",
   "fieldtype": "Data",
   "hidden": 0,
   "hide_border": 0,
   "hide_days": 0,
   "hide_seconds": 0,
   "idx": 17,
   "ignore_user_permissions": 0,
   "ignore_xss_filter": 0,
   "in_global_search": 0,
   "in_list_view": 0,
   "in_preview": 0,
   "in_standard_filter": 0,
   "insert_after": "informations_fiscales",
   "is_system_generated": 0,
   "is_virtual": 0,
   "label": "RC",
   "length": 0,
   "mandatory_depends_on": null,
   "modified": "2022-05-11 14:22:23.098397",
   "modified_by": "Administrator",
   "module": null,
   "name": "Delivery Note-rc",
   "no_copy": 0,
   "non_negative": 0,
   "options": null,
   "owner": "Administrator",
   "permlevel": 0,
   "precision": "",
   "print_hide": 0,
   "print_hide_if_no_value": 0,
   "print_width": null,
   "read_only": 0,
   "read_only_depends_on": null,
   "report_hide": 0,
   "reqd": 0,
   "search_index": 0,
   "translatable": 1,
   "unique": 0,
   "width": null
  },
  {
   "_assign": null,
   "_comments": null,
   "_liked_by": null,
   "_user_tags": null,
   "allow_in_quick_entry": 0,
   "allow_on_submit": 0,
   "bold": 0,
   "collapsible": 0,
   "collapsible_depends_on": null,
   "columns": 0,
   "creation": "2022-05-11 14:22:23.637905",
   "default": null,
   "depends_on": null,
   "description": null,
   "docstatus": 0,
   "dt": "Delivery Note",
   "fetch_from": "customer.nif",
   "fetch_if_empty": 0,
   "fieldname": "nif",
   "fieldtype": "Data",
   "hidden": 0,
   "hide_border": 0,
   "hide_days": 0,
   "hide_seconds": 0,
   "idx": 18,
   "ignore_user_permissions": 0,
   "ignore_xss_filter": 0,
   "in_global_search": 0,
   "in_list_view": 0,
   "in_preview": 0,
   "in_standard_filter": 0,
   "insert_after": "rc",
   "is_system_generated": 0,
   "is_virtual": 0,
   "label": "NIF",
   "length": 0,
   "mandatory_depends_on": null,
   "modified": "2022-05-11 14:22:23.637905",
   "modified_by": "Administrator",
   "module": null,
   "name": "Delivery Note-nif",
   "no_copy": 0,
   "non_negative": 0,
   "options": null,
   "owner": "Administrator",
   "permlevel": 0,
   "precision": "",
   "print_hide": 0,
   "print_hide_if_no_value": 0,
   "print_width": null,
   "read_only": 0,
   "read_only_depends_on": null,
   "report_hide": 0,
   "reqd": 0,
   "search_index": 0,
   "translatable": 1,
   "unique": 0,
   "width": null
  },
  {
   "_assign": null,
   "_comments": null,
   "_liked_by": null,
   "_user_tags": null,
   "allow_in_quick_entry": 0,
   "allow_on_submit": 0,
   "bold": 0,
   "collapsible": 0,
   "collapsible_depends_on": null,
   "columns": 0,
   "creation": "2022-05-11 14:22:24.230438",
   "default": null,
   "depends_on": null,
   "description": null,
   "docstatus": 0,
   "dt": "Delivery Note",
   "fetch_from": null,
   "fetch_if_empty": 0,
   "fieldname": "column_break_18",
   "fieldtype": "Column Break",
   "hidden": 0,
   "hide_border": 0,
   "hide_days": 0,
   "hide_seconds": 0,
   "idx": 19,
   "ignore_user_permissions": 0,
   "ignore_xss_filter": 0,
   "in_global_search": 0,
   "in_list_view": 0,
   "in_preview": 0,
   "in_standard_filter": 0,
   "insert_after": "nif",
   "is_system_generated": 0,
   "is_virtual": 0,
   "label": null,
   "length": 0,
   "mandatory_depends_on": null,
   "modified": "2022-05-11 14:22:24.230438",
   "modified_by": "Administrator",
   "module": null,
   "name": "Delivery Note-column_break_18",
   "no_copy": 0,
   "non_negative": 0,
   "options": null,
   "owner": "Administrator",
   "permlevel": 0,
   "precision": "",
   "print_hide": 0,
   "print_hide_if_no_value": 0,
   "print_width": null,
   "read_only": 0,
   "read_only_depends_on": null,
   "report_hide": 0,
   "reqd": 0,
   "search_index": 0,
   "translatable": 0,
   "unique": 0,
   "width": null
  },
  {
   "_assign": null,
   "_comments": null,
   "_liked_by": null,
   "_user_tags": null,
   "allow_in_quick_entry": 0,
   "allow_on_submit": 0,
   "bold": 0,
   "collapsible": 0,
   "collapsible_depends_on": null,
   "columns": 0,
   "creation": "2022-05-11 14:22:24.791265",
   "default": null,
   "depends_on": null,
   "description": null,
   "docstatus": 0,
   "dt": "Delivery Note",
   "fetch_from": "customer.af",
   "fetch_if_empty": 0,
   "fieldname": "af",
   "fieldtype": "Data",
   "hidden": 0,
   "hide_border": 0,
   "hide_days": 0,
   "hide_seconds": 0,
   "idx": 20,
   "ignore_user_permissions": 0,
   "ignore_xss_filter": 0,
   "in_global_search": 0,
   "in_list_view": 0,
   "in_preview": 0,
   "in_standard_filter": 0,
   "insert_after": "column_break_18",
   "is_system_generated": 0,
   "is_virtual": 0,
   "label": "AF",
   "length": 0,
   "mandatory_depends_on": null,
   "modified": "2022-05-11 14:22:24.791265",
   "modified_by": "Administrator",
   "module": null,
   "name": "Delivery Note-af",
   "no_copy": 0,
   "non_negative": 0,
   "options": null,
   "owner": "Administrator",
   "permlevel": 0,
   "precision": "",
   "print_hide": 0,
   "print_hide_if_no_value": 0,
   "print_width": null,
   "read_only": 0,
   "read_only_depends_on": null,
   "report_hide": 0,
   "reqd": 0,
   "search_index": 0,
   "translatable": 1,
   "unique": 0,
   "width": null
  },
  {
   "_assign": null,
   "_comments": null,
   "_liked_by": null,
   "_user_tags": null,
   "allow_in_quick_entry": 0,
   "allow_on_submit": 0,
   "bold": 0,
   "collapsible": 0,
   "collapsible_depends_on": null,
   "columns": 0,
   "creation": "2022-05-11 14:22:25.310692",
   "default": null,
   "depends_on": null,
   "description": null,
   "docstatus": 0,
   "dt": "Delivery Note",
   "fetch_from": "customer.nis",
   "fetch_if_empty": 0,
   "fieldname": "nis",
   "fieldtype": "Data",
   "hidden": 0,
   "hide_border": 0,
   "hide_days": 0,
   "hide_seconds": 0,
   "idx": 21,
   "ignore_user_permissions": 0,
   "ignore_xss_filter": 0,
   "in_global_search": 0,
   "in_list_view": 0,
   "in_preview": 0,
   "in_standard_filter": 0,
   "insert_after": "af",
   "is_system_generated": 0,
   "is_virtual": 0,
   "label": "NIS",
   "length": 0,
   "mandatory_depends_on": null,
   "modified": "2022-05-11 14:22:25.310692",
   "modified_by": "Administrator",
   "module": null,
   "name": "Delivery Note-nis",
   "no_copy": 0,
   "non_negative": 0,
   "options": null,
   "owner": "Administrator",
   "permlevel": 0,
   "precision": "",
   "print_hide": 0,
   "print_hide_if_no_value": 0,
   "print_width": null,
   "read_only": 0,
   "read_only_depends_on": null,
   "report_hide": 0,
   "reqd": 0,
   "search_index": 0,
   "translatable": 1,
   "unique": 0,
   "width": null
  },
  {
   "_assign": null,
   "_comments": null,
   "_liked_by": null,
   "_user_tags": null,
   "allow_in_quick_entry": 0,
   "allow_on_submit": 0,
   "bold": 0,
   "collapsible": 0,
   "collapsible_depends_on": "",
   "columns": 0,
   "creation": "2022-09-20 14:30:31.418178",
   "default": null,
   "depends_on": "",
   "description": null,
   "docstatus": 0,
   "dt": "Delivery Note",
   "fetch_from": null,
   "fetch_if_empty": 0,
   "fieldname": "informations_de_livraison",
   "fieldtype": "Section Break",
   "hidden": 0,
   "hide_border": 0,
   "hide_days": 0,
   "hide_seconds": 0,
   "idx": 64,
   "ignore_user_permissions": 0,
   "ignore_xss_filter": 0,
   "in_global_search": 0,
   "in_list_view": 0,
   "in_preview": 0,
   "in_standard_filter": 0,
   "insert_after": "pricing_rules",
   "is_system_generated": 0,
   "is_virtual": 0,
   "label": "Informations de livraison",
   "length": 0,
   "mandatory_depends_on": null,
   "modified": "2022-09-20 14:30:31.418178",
   "modified_by": "Administrator",
   "module": null,
   "name": "Delivery Note-informations_de_livraison",
   "no_copy": 0,
   "non_negative": 0,
   "options": null,
   "owner": "Administrator",
   "permlevel": 0,
   "precision": "",
   "print_hide": 0,
   "print_hide_if_no_value": 0,
   "print_width": null,
   "read_only": 0,
   "read_only_depends_on": null,
   "report_hide": 0,
   "reqd": 0,
   "search_index": 0,
   "translatable": 0,
   "unique": 0,
   "width": null
  },
  {
   "_assign": null,
   "_comments": null,
   "_liked_by": null,
   "_user_tags": null,
   "allow_in_quick_entry": 0,
   "allow_on_submit": 0,
   "bold": 0,
   "collapsible": 0,
   "collapsible_depends_on": null,
   "columns": 0,
   "creation": "2022-09-20 14:30:31.819281",
   "default": null,
   "depends_on": null,
   "description": null,
   "docstatus": 0,
   "dt": "Delivery Note",
   "fetch_from": null,
   "fetch_if_empty": 0,
   "fieldname": "nom_du_chauffeur",
   "fieldtype": "Data",
   "hidden": 0,
   "hide_border": 0,
   "hide_days": 0,
   "hide_seconds": 0,
   "idx": 65,
   "ignore_user_permissions": 0,
   "ignore_xss_filter": 0,
   "in_global_search": 0,
   "in_list_view": 0,
   "in_preview": 0,
   "in_standard_filter": 0,
   "insert_after": "informations_de_livraison",
   "is_system_generated": 0,
   "is_virtual": 0,
   "label": "Nom du chauffeur",
   "length": 0,
   "mandatory_depends_on": null,
   "modified": "2022-09-20 14:30:31.819281",
   "modified_by": "Administrator",
   "module": null,
   "name": "Delivery Note-nom_du_chauffeur",
   "no_copy": 0,
   "non_negative": 0,
   "options": null,
   "owner": "Administrator",
   "permlevel": 0,
   "precision": "",
   "print_hide": 0,
   "print_hide_if_no_value": 0,
   "print_width": null,
   "read_only": 0,
   "read_only_depends_on": null,
   "report_hide": 0,
   "reqd": 0,
   "search_index": 0,
   "translatable": 1,
   "unique": 0,
   "width": null
  },
  {
   "_assign": null,
   "_comments": null,
   "_liked_by": null,
   "_user_tags": null,
   "allow_in_quick_entry": 0,
   "allow_on_submit": 0,
   "bold": 0,
   "collapsible": 0,
   "collapsible_depends_on": null,
   "columns": 0,
   "creation": "2022-09-20 14:30:32.131896",
   "default": null,
   "depends_on": null,
   "description": null,
   "docstatus": 0,
   "dt": "Delivery Note",
   "fetch_from": null,
   "fetch_if_empty": 0,
   "fieldname": "pr\u00e9nom_du_chauffeur",
   "fieldtype": "Data",
   "hidden": 0,
   "hide_border": 0,
   "hide_days": 0,
   "hide_seconds": 0,
   "idx": 66,
   "ignore_user_permissions": 0,
   "ignore_xss_filter": 0,
   "in_global_search": 0,
   "in_list_view": 0,
   "in_preview": 0,
   "in_standard_filter": 0,
   "insert_after": "nom_du_chauffeur",
   "is_system_generated": 0,
   "is_virtual": 0,
   "label": "Pr\u00e9nom du chauffeur",
   "length": 0,
   "mandatory_depends_on": null,
   "modified": "2022-09-20 14:30:32.131896",
   "modified_by": "Administrator",
   "module": null,
   "name": "Delivery Note-pr\u00e9nom_du_chauffeur",
   "no_copy": 0,
   "non_negative": 0,
   "options": null,
   "owner": "Administrator",
   "permlevel": 0,
   "precision": "",
   "print_hide": 0,
   "print_hide_if_no_value": 0,
   "print_width": null,
   "read_only": 0,
   "read_only_depends_on": null,
   "report_hide": 0,
   "reqd": 0,
   "search_index": 0,
   "translatable": 1,
   "unique": 0,
   "width": null
  },
  {
   "_assign": null,
   "_comments": null,
   "_liked_by": null,
   "_user_tags": null,
   "allow_in_quick_entry": 0,
   "allow_on_submit": 0,
   "bold": 0,
   "collapsible": 0,
   "collapsible_depends_on": null,
   "columns": 0,
   "creation": "2022-09-20 14:30:32.480596",
   "default": null,
   "depends_on": null,
   "description": null,
   "docstatus": 0,
   "dt": "Delivery Note",
   "fetch_from": null,
   "fetch_if_empty": 0,
   "fieldname": "num\u00e9ro_du_permis",
   "fieldtype": "Data",
   "hidden": 0,
   "hide_border": 0,
   "hide_days": 0,
   "hide_seconds": 0,
   "idx": 67,
   "ignore_user_permissions": 0,
   "ignore_xss_filter": 0,
   "in_global_search": 0,
   "in_list_view": 0,
   "in_preview": 0,
   "in_standard_filter": 0,
   "insert_after": "pr\u00e9nom_du_chauffeur",
   "is_system_generated": 0,
   "is_virtual": 0,
   "label": "Num\u00e9ro du permis",
   "length": 0,
   "mandatory_depends_on": null,
   "modified": "2022-09-20 14:30:32.480596",
   "modified_by": "Administrator",
   "module": null,
   "name": "Delivery Note-num\u00e9ro_du_permis",
   "no_copy": 0,
   "non_negative": 0,
   "options": null,
   "owner": "Administrator",
   "permlevel": 0,
   "precision": "",
   "print_hide": 0,
   "print_hide_if_no_value": 0,
   "print_width": null,
   "read_only": 0,
   "read_only_depends_on": null,
   "report_hide": 0,
   "reqd": 0,
   "search_index": 0,
   "translatable": 1,
   "unique": 0,
   "width": null
  },
  {
   "_assign": null,
   "_comments": null,
   "_liked_by": null,
   "_user_tags": null,
   "allow_in_quick_entry": 0,
   "allow_on_submit": 0,
   "bold": 0,
   "collapsible": 0,
   "collapsible_depends_on": null,
   "columns": 0,
   "creation": "2022-09-20 14:30:32.918207",
   "default": null,
   "depends_on": null,
   "description": null,
   "docstatus": 0,
   "dt": "Delivery Note",
   "fetch_from": null,
   "fetch_if_empty": 0,
   "fieldname": "column_break_67",
   "fieldtype": "Column Break",
   "hidden": 0,
   "hide_border": 0,
   "hide_days": 0,
   "hide_seconds": 0,
   "idx": 68,
   "ignore_user_permissions": 0,
   "ignore_xss_filter": 0,
   "in_global_search": 0,
   "in_list_view": 0,
   "in_preview": 0,
   "in_standard_filter": 0,
   "insert_after": "num\u00e9ro_du_permis",
   "is_system_generated": 0,
   "is_virtual": 0,
   "label": null,
   "length": 0,
   "mandatory_depends_on": null,
   "modified": "2022-09-20 14:30:32.918207",
   "modified_by": "Administrator",
   "module": null,
   "name": "Delivery Note-column_break_67",
   "no_copy": 0,
   "non_negative": 0,
   "options": null,
   "owner": "Administrator",
   "permlevel": 0,
   "precision": "",
   "print_hide": 0,
   "print_hide_if_no_value": 0,
   "print_width": null,
   "read_only": 0,
   "read_only_depends_on": null,
   "report_hide": 0,
   "reqd": 0,
   "search_index": 0,
   "translatable": 0,
   "unique": 0,
   "width": null
  },
  {
   "_assign": null,
   "_comments": null,
   "_liked_by": null,
   "_user_tags": null,
   "allow_in_quick_entry": 0,
   "allow_on_submit": 0,
   "bold": 0,
   "collapsible": 0,
   "collapsible_depends_on": null,
   "columns": 0,
   "creation": "2022-09-20 14:30:33.357812",
   "default": null,
   "depends_on": null,
   "description": null,
   "docstatus": 0,
   "dt": "Delivery Note",
   "fetch_from": null,
   "fetch_if_empty": 0,
   "fieldname": "marque_du_camion",
   "fieldtype": "Data",
   "hidden": 0,
   "hide_border": 0,
   "hide_days": 0,
   "hide_seconds": 0,
   "idx": 69,
   "ignore_user_permissions": 0,
   "ignore_xss_filter": 0,
   "in_global_search": 0,
   "in_list_view": 0,
   "in_preview": 0,
   "in_standard_filter": 0,
   "insert_after": "column_break_67",
   "is_system_generated": 0,
   "is_virtual": 0,
   "label": "Marque du camion",
   "length": 0,
   "mandatory_depends_on": null,
   "modified": "2022-09-20 14:30:33.357812",
   "modified_by": "Administrator",
   "module": null,
   "name": "Delivery Note-marque_du_camion",
   "no_copy": 0,
   "non_negative": 0,
   "options": null,
   "owner": "Administrator",
   "permlevel": 0,
   "precision": "",
   "print_hide": 0,
   "print_hide_if_no_value": 0,
   "print_width": null,
   "read_only": 0,
   "read_only_depends_on": null,
   "report_hide": 0,
   "reqd": 0,
   "search_index": 0,
   "translatable": 1,
   "unique": 0,
   "width": null
  },
  {
   "_assign": null,
   "_comments": null,
   "_liked_by": null,
   "_user_tags": null,
   "allow_in_quick_entry": 0,
   "allow_on_submit": 0,
   "bold": 0,
   "collapsible": 0,
   "collapsible_depends_on": null,
   "columns": 0,
   "creation": "2022-09-20 14:30:33.665450",
   "default": null,
   "depends_on": null,
   "description": null,
   "docstatus": 0,
   "dt": "Delivery Note",
   "fetch_from": null,
   "fetch_if_empty": 0,
   "fieldname": "immatriculation_du_camion",
   "fieldtype": "Data",
   "hidden": 0,
   "hide_border": 0,
   "hide_days": 0,
   "hide_seconds": 0,
   "idx": 70,
   "ignore_user_permissions": 0,
   "ignore_xss_filter": 0,
   "in_global_search": 0,
   "in_list_view": 0,
   "in_preview": 0,
   "in_standard_filter": 0,
   "insert_after": "marque_du_camion",
   "is_system_generated": 0,
   "is_virtual": 0,
   "label": "Immatriculation du camion",
   "length": 0,
   "mandatory_depends_on": null,
   "modified": "2022-09-20 14:30:33.665450",
   "modified_by": "Administrator",
   "module": null,
   "name": "Delivery Note-immatriculation_du_camion",
   "no_copy": 0,
   "non_negative": 0,
   "options": null,
   "owner": "Administrator",
   "permlevel": 0,
   "precision": "",
   "print_hide": 0,
   "print_hide_if_no_value": 0,
   "print_width": null,
   "read_only": 0,
   "read_only_depends_on": null,
   "report_hide": 0,
   "reqd": 0,
   "search_index": 0,
   "translatable": 1,
   "unique": 0,
   "width": null
  },
  {
   "_assign": null,
   "_comments": null,
   "_liked_by": null,
   "_user_tags": null,
   "allow_in_quick_entry": 0,
   "allow_on_submit": 0,
   "bold": 0,
   "collapsible": 0,
   "collapsible_depends_on": null,
   "columns": 0,
   "creation": "2022-09-20 14:47:28.049334",
   "default": null,
   "depends_on": null,
   "description": null,
   "docstatus": 0,
   "dt": "Delivery Note",
   "fetch_from": null,
   "fetch_if_empty": 0,
   "fieldname": "destination",
   "fieldtype": "Data",
   "hidden": 0,
   "hide_border": 0,
   "hide_days": 0,
   "hide_seconds": 0,
   "idx": 71,
   "ignore_user_permissions": 0,
   "ignore_xss_filter": 0,
   "in_global_search": 0,
   "in_list_view": 0,
   "in_preview": 0,
   "in_standard_filter": 0,
   "insert_after": "immatriculation_du_camion",
   "is_system_generated": 0,
   "is_virtual": 0,
   "label": "Destination",
   "length": 0,
   "mandatory_depends_on": null,
   "modified": "2022-09-20 14:47:28.049334",
   "modified_by": "Administrator",
   "module": null,
   "name": "Delivery Note-destination",
   "no_copy": 0,
   "non_negative": 0,
   "options": null,
   "owner": "Administrator",
   "permlevel": 0,
   "precision": "",
   "print_hide": 0,
   "print_hide_if_no_value": 0,
   "print_width": null,
   "read_only": 0,
   "read_only_depends_on": null,
   "report_hide": 0,
   "reqd": 0,
   "search_index": 0,
   "translatable": 1,
   "unique": 0,
   "width": null
  }
 ],
 "custom_perms": [],
 "doctype": "Delivery Note",
 "links": [],
 "property_setters": [
  {
   "_assign": null,
   "_comments": null,
   "_liked_by": null,
   "_user_tags": null,
   "creation": "2022-09-28 14:34:22.839946",
   "default_value": null,
   "doc_type": "Delivery Note",
   "docstatus": 0,
   "doctype_or_field": "DocField",
   "field_name": "lr_date",
   "idx": 0,
   "is_system_generated": 0,
   "modified": "2022-09-28 14:34:22.839946",
   "modified_by": "Administrator",
   "module": null,
   "name": "Delivery Note-lr_date-hidden",
   "owner": "Administrator",
   "property": "hidden",
   "property_type": "Check",
   "row_name": null,
   "value": "1"
  },
  {
   "_assign": null,
   "_comments": null,
   "_liked_by": null,
   "_user_tags": null,
   "creation": "2022-09-28 14:34:22.746118",
   "default_value": null,
   "doc_type": "Delivery Note",
   "docstatus": 0,
   "doctype_or_field": "DocField",
   "field_name": "driver_name",
   "idx": 0,
   "is_system_generated": 0,
   "modified": "2022-09-28 14:34:22.746118",
   "modified_by": "Administrator",
   "module": null,
   "name": "Delivery Note-driver_name-hidden",
   "owner": "Administrator",
   "property": "hidden",
   "property_type": "Check",
   "row_name": null,
   "value": "1"
  },
  {
   "_assign": null,
   "_comments": null,
   "_liked_by": null,
   "_user_tags": null,
   "creation": "2022-09-28 14:34:22.646888",
   "default_value": null,
   "doc_type": "Delivery Note",
   "docstatus": 0,
   "doctype_or_field": "DocField",
   "field_name": "transporter_name",
   "idx": 0,
   "is_system_generated": 0,
   "modified": "2022-09-28 14:34:22.646888",
   "modified_by": "Administrator",
   "module": null,
   "name": "Delivery Note-transporter_name-hidden",
   "owner": "Administrator",
   "property": "hidden",
   "property_type": "Check",
   "row_name": null,
   "value": "1"
  },
  {
   "_assign": null,
   "_comments": null,
   "_liked_by": null,
   "_user_tags": null,
   "creation": "2022-09-28 14:34:22.558827",
   "default_value": null,
   "doc_type": "Delivery Note",
   "docstatus": 0,
   "doctype_or_field": "DocField",
   "field_name": "col_break34",
   "idx": 0,
   "is_system_generated": 0,
   "modified": "2022-09-28 14:34:22.558827",
   "modified_by": "Administrator",
   "module": null,
   "name": "Delivery Note-col_break34-hidden",
   "owner": "Administrator",
   "property": "hidden",
   "property_type": "Check",
   "row_name": null,
   "value": "1"
  },
  {
   "_assign": null,
   "_comments": null,
   "_liked_by": null,
   "_user_tags": null,
   "creation": "2022-09-28 14:34:22.468483",
   "default_value": null,
   "doc_type": "Delivery Note",
   "docstatus": 0,
   "doctype_or_field": "DocField",
   "field_name": "vehicle_no",
   "idx": 0,
   "is_system_generated": 0,
   "modified": "2022-09-28 14:34:22.468483",
   "modified_by": "Administrator",
   "module": null,
   "name": "Delivery Note-vehicle_no-hidden",
   "owner": "Administrator",
   "property": "hidden",
   "property_type": "Check",
   "row_name": null,
   "value": "1"
  },
  {
   "_assign": null,
   "_comments": null,
   "_liked_by": null,
   "_user_tags": null,
   "creation": "2022-09-28 14:34:22.378566",
   "default_value": null,
   "doc_type": "Delivery Note",
   "docstatus": 0,
   "doctype_or_field": "DocField",
   "field_name": "lr_no",
   "idx": 0,
   "is_system_generated": 0,
   "modified": "2022-09-28 14:34:22.378566",
   "modified_by": "Administrator",
   "module": null,
   "name": "Delivery Note-lr_no-hidden",
   "owner": "Administrator",
   "property": "hidden",
   "property_type": "Check",
   "row_name": null,
   "value": "1"
  },
  {
   "_assign": null,
   "_comments": null,
   "_liked_by": null,
   "_user_tags": null,
   "creation": "2022-09-28 14:34:22.214709",
   "default_value": null,
   "doc_type": "Delivery Note",
   "docstatus": 0,
   "doctype_or_field": "DocField",
   "field_name": "driver",
   "idx": 0,
   "is_system_generated": 0,
   "modified": "2022-09-28 14:34:22.214709",
   "modified_by": "Administrator",
   "module": null,
   "name": "Delivery Note-driver-hidden",
   "owner": "Administrator",
   "property": "hidden",
   "property_type": "Check",
   "row_name": null,
   "value": "1"
  },
  {
   "_assign": null,
   "_comments": null,
   "_liked_by": null,
   "_user_tags": null,
   "creation": "2022-09-28 14:34:22.118709",
   "default_value": null,
   "doc_type": "Delivery Note",
   "docstatus": 0,
   "doctype_or_field": "DocField",
   "field_name": "transporter",
   "idx": 0,
   "is_system_generated": 0,
   "modified": "2022-09-28 14:34:22.118709",
   "modified_by": "Administrator",
   "module": null,
   "name": "Delivery Note-transporter-hidden",
   "owner": "Administrator",
   "property": "hidden",
   "property_type": "Check",
   "row_name": null,
   "value": "1"
  },
  {
   "_assign": null,
   "_comments": null,
   "_liked_by": null,
   "_user_tags": null,
   "creation": "2022-09-28 14:34:22.007710",
   "default_value": null,
   "doc_type": "Delivery Note",
   "docstatus": 0,
   "doctype_or_field": "DocField",
   "field_name": "transporter_info",
   "idx": 0,
   "is_system_generated": 0,
   "modified": "2022-09-28 14:34:22.007710",
   "modified_by": "Administrator",
   "module": null,
   "name": "Delivery Note-transporter_info-hidden",
   "owner": "Administrator",
   "property": "hidden",
   "property_type": "Check",
   "row_name": null,
   "value": "1"
  },
  {
   "_assign": null,
   "_comments": null,
   "_liked_by": null,
   "_user_tags": null,
   "creation": "2022-09-28 14:33:34.192220",
   "default_value": null,
   "doc_type": "Delivery Note",
   "docstatus": 0,
   "doctype_or_field": "DocField",
   "field_name": "sales_team",
   "idx": 0,
   "is_system_generated": 0,
   "modified": "2022-09-28 14:33:34.192220",
   "modified_by": "Administrator",
   "module": null,
   "name": "Delivery Note-sales_team-hidden",
   "owner": "Administrator",
   "property": "hidden",
   "property_type": "Check",
   "row_name": null,
   "value": "1"
  },
  {
   "_assign": null,
   "_comments": null,
   "_liked_by": null,
   "_user_tags": null,
   "creation": "2022-09-28 14:33:34.106039",
   "default_value": null,
   "doc_type": "Delivery Note",
   "docstatus": 0,
   "doctype_or_field": "DocField",
   "field_name": "section_break1",
   "idx": 0,
   "is_system_generated": 0,
   "modified": "2022-09-28 14:33:34.106039",
   "modified_by": "Administrator",
   "module": null,
   "name": "Delivery Note-section_break1-hidden",
   "owner": "Administrator",
   "property": "hidden",
   "property_type": "Check",
   "row_name": null,
   "value": "1"
  },
  {
   "_assign": null,
   "_comments": null,
   "_liked_by": null,
   "_user_tags": null,
   "creation": "2022-09-28 14:33:34.013702",
   "default_value": null,
   "doc_type": "Delivery Note",
   "docstatus": 0,
   "doctype_or_field": "DocField",
   "field_name": "total_commission",
   "idx": 0,
   "is_system_generated": 0,
   "modified": "2022-09-28 14:33:34.013702",
   "modified_by": "Administrator",
   "module": null,
   "name": "Delivery Note-total_commission-hidden",
   "owner": "Administrator",
   "property": "hidden",
   "property_type": "Check",
   "row_name": null,
   "value": "1"
  },
  {
   "_assign": null,
   "_comments": null,
   "_liked_by": null,
   "_user_tags": null,
   "creation": "2022-09-28 14:33:33.925303",
   "default_value": null,
   "doc_type": "Delivery Note",
   "docstatus": 0,
   "doctype_or_field": "DocField",
   "field_name": "commission_rate",
   "idx": 0,
   "is_system_generated": 0,
   "modified": "2022-09-28 14:33:33.925303",
   "modified_by": "Administrator",
   "module": null,
   "name": "Delivery Note-commission_rate-hidden",
   "owner": "Administrator",
   "property": "hidden",
   "property_type": "Check",
   "row_name": null,
   "value": "1"
  },
  {
   "_assign": null,
   "_comments": null,
   "_liked_by": null,
   "_user_tags": null,
   "creation": "2022-09-28 14:33:33.768313",
   "default_value": null,
   "doc_type": "Delivery Note",
   "docstatus": 0,
   "doctype_or_field": "DocField",
   "field_name": "amount_eligible_for_commission",
   "idx": 0,
   "is_system_generated": 0,
   "modified": "2022-09-28 14:33:33.768313",
   "modified_by": "Administrator",
   "module": null,
   "name": "Delivery Note-amount_eligible_for_commission-hidden",
   "owner": "Administrator",
   "property": "hidden",
   "property_type": "Check",
   "row_name": null,
   "value": "1"
  },
  {
   "_assign": null,
   "_comments": null,
   "_liked_by": null,
   "_user_tags": null,
   "creation": "2022-09-28 14:33:33.679113",
   "default_value": null,
   "doc_type": "Delivery Note",
   "docstatus": 0,
   "doctype_or_field": "DocField",
   "field_name": "column_break7",
   "idx": 0,
   "is_system_generated": 0,
   "modified": "2022-09-28 14:33:33.679113",
   "modified_by": "Administrator",
   "module": null,
   "name": "Delivery Note-column_break7-hidden",
   "owner": "Administrator",
   "property": "hidden",
   "property_type": "Check",
   "row_name": null,
   "value": "1"
  },
  {
   "_assign": null,
   "_comments": null,
   "_liked_by": null,
   "_user_tags": null,
   "creation": "2022-09-28 14:33:33.586941",
   "default_value": null,
   "doc_type": "Delivery Note",
   "docstatus": 0,
   "doctype_or_field": "DocField",
   "field_name": "sales_partner",
   "idx": 0,
   "is_system_generated": 0,
   "modified": "2022-09-28 14:33:33.586941",
   "modified_by": "Administrator",
   "module": null,
   "name": "Delivery Note-sales_partner-hidden",
   "owner": "Administrator",
   "property": "hidden",
   "property_type": "Check",
   "row_name": null,
   "value": "1"
  },
  {
   "_assign": null,
   "_comments": null,
   "_liked_by": null,
   "_user_tags": null,
   "creation": "2022-09-28 14:33:33.479485",
   "default_value": null,
   "doc_type": "Delivery Note",
   "docstatus": 0,
   "doctype_or_field": "DocField",
   "field_name": "sales_team_section_break",
   "idx": 0,
   "is_system_generated": 0,
   "modified": "2022-09-28 14:33:33.479485",
   "modified_by": "Administrator",
   "module": null,
   "name": "Delivery Note-sales_team_section_break-hidden",
   "owner": "Administrator",
   "property": "hidden",
   "property_type": "Check",
   "row_name": null,
   "value": "1"
  },
  {
   "_assign": null,
   "_comments": null,
   "_liked_by": null,
   "_user_tags": null,
   "creation": "2022-09-28 14:32:53.566759",
   "default_value": null,
   "doc_type": "Delivery Note",
   "docstatus": 0,
   "doctype_or_field": "DocField",
   "field_name": "group_same_items",
   "idx": 0,
   "is_system_generated": 0,
   "modified": "2022-09-28 14:32:53.566759",
   "modified_by": "Administrator",
   "module": null,
   "name": "Delivery Note-group_same_items-hidden",
   "owner": "Administrator",
   "property": "hidden",
   "property_type": "Check",
   "row_name": null,
   "value": "1"
  },
  {
   "_assign": null,
   "_comments": null,
   "_liked_by": null,
   "_user_tags": null,
   "creation": "2022-09-28 14:32:53.478202",
   "default_value": null,
   "doc_type": "Delivery Note",
   "docstatus": 0,
   "doctype_or_field": "DocField",
   "field_name": "print_without_amount",
   "idx": 0,
   "is_system_generated": 0,
   "modified": "2022-09-28 14:32:53.478202",
   "modified_by": "Administrator",
   "module": null,
   "name": "Delivery Note-print_without_amount-hidden",
   "owner": "Administrator",
   "property": "hidden",
   "property_type": "Check",
   "row_name": null,
   "value": "1"
  },
  {
   "_assign": null,
   "_comments": null,
   "_liked_by": null,
   "_user_tags": null,
   "creation": "2022-09-28 14:32:53.322170",
   "default_value": null,
   "doc_type": "Delivery Note",
   "docstatus": 0,
   "doctype_or_field": "DocField",
   "field_name": "column_break_88",
   "idx": 0,
   "is_system_generated": 0,
   "modified": "2022-09-28 14:32:53.322170",
   "modified_by": "Administrator",
   "module": null,
   "name": "Delivery Note-column_break_88-hidden",
   "owner": "Administrator",
   "property": "hidden",
   "property_type": "Check",
   "row_name": null,
   "value": "1"
  },
  {
   "_assign": null,
   "_comments": null,
   "_liked_by": null,
   "_user_tags": null,
   "creation": "2022-09-28 14:32:53.136341",
   "default_value": null,
   "doc_type": "Delivery Note",
   "docstatus": 0,
   "doctype_or_field": "DocField",
   "field_name": "language",
   "idx": 0,
   "is_system_generated": 0,
   "modified": "2022-09-28 14:32:53.136341",
   "modified_by": "Administrator",
   "module": null,
   "name": "Delivery Note-language-hidden",
   "owner": "Administrator",
   "property": "hidden",
   "property_type": "Check",
   "row_name": null,
   "value": "1"
  },
  {
   "_assign": null,
   "_comments": null,
   "_liked_by": null,
   "_user_tags": null,
   "creation": "2022-09-28 14:32:53.038556",
   "default_value": null,
   "doc_type": "Delivery Note",
   "docstatus": 0,
   "doctype_or_field": "DocField",
   "field_name": "select_print_heading",
   "idx": 0,
   "is_system_generated": 0,
   "modified": "2022-09-28 14:32:53.038556",
   "modified_by": "Administrator",
   "module": null,
   "name": "Delivery Note-select_print_heading-hidden",
   "owner": "Administrator",
   "property": "hidden",
   "property_type": "Check",
   "row_name": null,
   "value": "1"
  },
  {
   "_assign": null,
   "_comments": null,
   "_liked_by": null,
   "_user_tags": null,
   "creation": "2022-09-28 14:32:52.872112",
   "default_value": null,
   "doc_type": "Delivery Note",
   "docstatus": 0,
   "doctype_or_field": "DocField",
   "field_name": "letter_head",
   "idx": 0,
   "is_system_generated": 0,
   "modified": "2022-09-28 14:32:52.872112",
   "modified_by": "Administrator",
   "module": null,
   "name": "Delivery Note-letter_head-hidden",
   "owner": "Administrator",
   "property": "hidden",
   "property_type": "Check",
   "row_name": null,
   "value": "1"
  },
  {
   "_assign": null,
   "_comments": null,
   "_liked_by": null,
   "_user_tags": null,
   "creation": "2022-09-28 14:32:52.778692",
   "default_value": null,
   "doc_type": "Delivery Note",
   "docstatus": 0,
   "doctype_or_field": "DocField",
   "field_name": "printing_details",
   "idx": 0,
   "is_system_generated": 0,
   "modified": "2022-09-28 14:32:52.778692",
   "modified_by": "Administrator",
   "module": null,
   "name": "Delivery Note-printing_details-hidden",
   "owner": "Administrator",
   "property": "hidden",
   "property_type": "Check",
   "row_name": null,
   "value": "1"
  },
  {
   "_assign": null,
   "_comments": null,
   "_liked_by": null,
   "_user_tags": null,
   "creation": "2022-09-28 14:32:52.684243",
   "default_value": null,
   "doc_type": "Delivery Note",
   "docstatus": 0,
   "doctype_or_field": "DocField",
   "field_name": "territory",
   "idx": 0,
   "is_system_generated": 0,
   "modified": "2022-09-28 14:32:52.684243",
   "modified_by": "Administrator",
   "module": null,
   "name": "Delivery Note-territory-hidden",
   "owner": "Administrator",
   "property": "hidden",
   "property_type": "Check",
   "row_name": null,
   "value": "1"
  },
  {
   "_assign": null,
   "_comments": null,
   "_liked_by": null,
   "_user_tags": null,
   "creation": "2022-09-28 14:32:52.585908",
   "default_value": null,
   "doc_type": "Delivery Note",
   "docstatus": 0,
   "doctype_or_field": "DocField",
   "field_name": "per_billed",
   "idx": 0,
   "is_system_generated": 0,
   "modified": "2022-09-28 14:32:52.585908",
   "modified_by": "Administrator",
   "module": null,
   "name": "Delivery Note-per_billed-hidden",
   "owner": "Administrator",
   "property": "hidden",
   "property_type": "Check",
   "row_name": null,
   "value": "1"
  },
  {
   "_assign": null,
   "_comments": null,
   "_liked_by": null,
   "_user_tags": null,
   "creation": "2022-09-28 14:32:52.500326",
   "default_value": null,
   "doc_type": "Delivery Note",
   "docstatus": 0,
   "doctype_or_field": "DocField",
   "field_name": "inter_company_reference",
   "idx": 0,
   "is_system_generated": 0,
   "modified": "2022-09-28 14:32:52.500326",
   "modified_by": "Administrator",
   "module": null,
   "name": "Delivery Note-inter_company_reference-hidden",
   "owner": "Administrator",
   "property": "hidden",
   "property_type": "Check",
   "row_name": null,
   "value": "1"
  },
  {
   "_assign": null,
   "_comments": null,
   "_liked_by": null,
   "_user_tags": null,
   "creation": "2022-09-28 14:32:52.350208",
   "default_value": null,
   "doc_type": "Delivery Note",
   "docstatus": 0,
   "doctype_or_field": "DocField",
   "field_name": "represents_company",
   "idx": 0,
   "is_system_generated": 0,
   "modified": "2022-09-28 14:32:52.350208",
   "modified_by": "Administrator",
   "module": null,
   "name": "Delivery Note-represents_company-hidden",
   "owner": "Administrator",
   "property": "hidden",
   "property_type": "Check",
   "row_name": null,
   "value": "1"
  },
  {
   "_assign": null,
   "_comments": null,
   "_liked_by": null,
   "_user_tags": null,
   "creation": "2022-09-28 14:32:52.250919",
   "default_value": null,
   "doc_type": "Delivery Note",
   "docstatus": 0,
   "doctype_or_field": "DocField",
   "field_name": "is_internal_customer",
   "idx": 0,
   "is_system_generated": 0,
   "modified": "2022-09-28 14:32:52.250919",
   "modified_by": "Administrator",
   "module": null,
   "name": "Delivery Note-is_internal_customer-hidden",
   "owner": "Administrator",
   "property": "hidden",
   "property_type": "Check",
   "row_name": null,
   "value": "1"
  },
  {
   "_assign": null,
   "_comments": null,
   "_liked_by": null,
   "_user_tags": null,
   "creation": "2022-09-28 14:32:52.142678",
   "default_value": null,
   "doc_type": "Delivery Note",
   "docstatus": 0,
   "doctype_or_field": "DocField",
   "field_name": "column_break5",
   "idx": 0,
   "is_system_generated": 0,
   "modified": "2022-09-28 14:32:52.142678",
   "modified_by": "Administrator",
   "module": null,
   "name": "Delivery Note-column_break5-hidden",
   "owner": "Administrator",
   "property": "hidden",
   "property_type": "Check",
   "row_name": null,
   "value": "1"
  },
  {
   "_assign": null,
   "_comments": null,
   "_liked_by": null,
   "_user_tags": null,
   "creation": "2022-09-28 14:32:52.037326",
   "default_value": null,
   "doc_type": "Delivery Note",
   "docstatus": 0,
   "doctype_or_field": "DocField",
   "field_name": "source",
   "idx": 0,
   "is_system_generated": 0,
   "modified": "2022-09-28 14:32:52.037326",
   "modified_by": "Administrator",
   "module": null,
   "name": "Delivery Note-source-hidden",
   "owner": "Administrator",
   "property": "hidden",
   "property_type": "Check",
   "row_name": null,
   "value": "1"
  },
  {
   "_assign": null,
   "_comments": null,
   "_liked_by": null,
   "_user_tags": null,
   "creation": "2022-09-28 14:32:51.827131",
   "default_value": null,
   "doc_type": "Delivery Note",
   "docstatus": 0,
   "doctype_or_field": "DocField",
   "field_name": "campaign",
   "idx": 0,
   "is_system_generated": 0,
   "modified": "2022-09-28 14:32:51.827131",
   "modified_by": "Administrator",
   "module": null,
   "name": "Delivery Note-campaign-hidden",
   "owner": "Administrator",
   "property": "hidden",
   "property_type": "Check",
   "row_name": null,
   "value": "1"
  },
  {
   "_assign": null,
   "_comments": null,
   "_liked_by": null,
   "_user_tags": null,
   "creation": "2022-09-28 14:32:51.725385",
   "default_value": null,
   "doc_type": "Delivery Note",
   "docstatus": 0,
   "doctype_or_field": "DocField",
   "field_name": "more_info",
   "idx": 0,
   "is_system_generated": 0,
   "modified": "2022-09-28 14:32:51.725385",
   "modified_by": "Administrator",
   "module": null,
   "name": "Delivery Note-more_info-hidden",
   "owner": "Administrator",
   "property": "hidden",
   "property_type": "Check",
   "row_name": null,
   "value": "1"
  },
  {
   "_assign": null,
   "_comments": null,
   "_liked_by": null,
   "_user_tags": null,
   "creation": "2022-09-28 14:30:50.726283",
   "default_value": null,
   "doc_type": "Delivery Note",
   "docstatus": 0,
   "doctype_or_field": "DocField",
   "field_name": "total_taxes_and_charges",
   "idx": 0,
   "is_system_generated": 0,
   "modified": "2022-09-28 14:30:50.726283",
   "modified_by": "Administrator",
   "module": null,
   "name": "Delivery Note-total_taxes_and_charges-hidden",
   "owner": "Administrator",
   "property": "hidden",
   "property_type": "Check",
   "row_name": null,
   "value": "1"
  },
  {
   "_assign": null,
   "_comments": null,
   "_liked_by": null,
   "_user_tags": null,
   "creation": "2022-09-28 14:30:50.638258",
   "default_value": null,
   "doc_type": "Delivery Note",
   "docstatus": 0,
   "doctype_or_field": "DocField",
   "field_name": "column_break_47",
   "idx": 0,
   "is_system_generated": 0,
   "modified": "2022-09-28 14:30:50.638258",
   "modified_by": "Administrator",
   "module": null,
   "name": "Delivery Note-column_break_47-hidden",
   "owner": "Administrator",
   "property": "hidden",
   "property_type": "Check",
   "row_name": null,
   "value": "1"
  },
  {
   "_assign": null,
   "_comments": null,
   "_liked_by": null,
   "_user_tags": null,
   "creation": "2022-09-28 14:30:50.542357",
   "default_value": null,
   "doc_type": "Delivery Note",
   "docstatus": 0,
   "doctype_or_field": "DocField",
   "field_name": "base_total_taxes_and_charges",
   "idx": 0,
   "is_system_generated": 0,
   "modified": "2022-09-28 14:30:50.542357",
   "modified_by": "Administrator",
   "module": null,
   "name": "Delivery Note-base_total_taxes_and_charges-hidden",
   "owner": "Administrator",
   "property": "hidden",
   "property_type": "Check",
   "row_name": null,
   "value": "1"
  },
  {
   "_assign": null,
   "_comments": null,
   "_liked_by": null,
   "_user_tags": null,
   "creation": "2022-09-28 14:30:50.450519",
   "default_value": null,
   "doc_type": "Delivery Note",
   "docstatus": 0,
   "doctype_or_field": "DocField",
   "field_name": "section_break_44",
   "idx": 0,
   "is_system_generated": 0,
   "modified": "2022-09-28 14:30:50.450519",
   "modified_by": "Administrator",
   "module": null,
   "name": "Delivery Note-section_break_44-hidden",
   "owner": "Administrator",
   "property": "hidden",
   "property_type": "Check",
   "row_name": null,
   "value": "1"
  },
  {
   "_assign": null,
   "_comments": null,
   "_liked_by": null,
   "_user_tags": null,
   "creation": "2022-09-28 14:30:50.349461",
   "default_value": null,
   "doc_type": "Delivery Note",
   "docstatus": 0,
   "doctype_or_field": "DocField",
   "field_name": "other_charges_calculation",
   "idx": 0,
   "is_system_generated": 0,
   "modified": "2022-09-28 14:30:50.349461",
   "modified_by": "Administrator",
   "module": null,
   "name": "Delivery Note-other_charges_calculation-hidden",
   "owner": "Administrator",
   "property": "hidden",
   "property_type": "Check",
   "row_name": null,
   "value": "1"
  },
  {
   "_assign": null,
   "_comments": null,
   "_liked_by": null,
   "_user_tags": null,
   "creation": "2022-09-28 14:30:50.163443",
   "default_value": null,
   "doc_type": "Delivery Note",
   "docstatus": 0,
   "doctype_or_field": "DocField",
   "field_name": "sec_tax_breakup",
   "idx": 0,
   "is_system_generated": 0,
   "modified": "2022-09-28 14:30:50.163443",
   "modified_by": "Administrator",
   "module": null,
   "name": "Delivery Note-sec_tax_breakup-hidden",
   "owner": "Administrator",
   "property": "hidden",
   "property_type": "Check",
   "row_name": null,
   "value": "1"
  },
  {
   "_assign": null,
   "_comments": null,
   "_liked_by": null,
   "_user_tags": null,
   "creation": "2022-09-28 14:29:51.658686",
   "default_value": null,
   "doc_type": "Delivery Note",
   "docstatus": 0,
   "doctype_or_field": "DocField",
   "field_name": "totals",
   "idx": 0,
   "is_system_generated": 0,
   "modified": "2022-09-28 14:29:51.658686",
   "modified_by": "Administrator",
   "module": null,
   "name": "Delivery Note-totals-hidden",
   "owner": "Administrator",
   "property": "hidden",
   "property_type": "Check",
   "row_name": null,
   "value": "1"
  },
  {
   "_assign": null,
   "_comments": null,
   "_liked_by": null,
   "_user_tags": null,
   "creation": "2022-09-28 14:29:51.580217",
   "default_value": null,
   "doc_type": "Delivery Note",
   "docstatus": 0,
   "doctype_or_field": "DocField",
   "field_name": "discount_amount",
   "idx": 0,
   "is_system_generated": 0,
   "modified": "2022-09-28 14:29:51.580217",
   "modified_by": "Administrator",
   "module": null,
   "name": "Delivery Note-discount_amount-hidden",
   "owner": "Administrator",
   "property": "hidden",
   "property_type": "Check",
   "row_name": null,
   "value": "1"
  },
  {
   "_assign": null,
   "_comments": null,
   "_liked_by": null,
   "_user_tags": null,
   "creation": "2022-09-28 14:29:51.384351",
   "default_value": null,
   "doc_type": "Delivery Note",
   "docstatus": 0,
   "doctype_or_field": "DocField",
   "field_name": "additional_discount_percentage",
   "idx": 0,
   "is_system_generated": 0,
   "modified": "2022-09-28 14:29:51.384351",
   "modified_by": "Administrator",
   "module": null,
   "name": "Delivery Note-additional_discount_percentage-hidden",
   "owner": "Administrator",
   "property": "hidden",
   "property_type": "Check",
   "row_name": null,
   "value": "1"
  },
  {
   "_assign": null,
   "_comments": null,
   "_liked_by": null,
   "_user_tags": null,
   "creation": "2022-09-28 14:29:51.197203",
   "default_value": null,
   "doc_type": "Delivery Note",
   "docstatus": 0,
   "doctype_or_field": "DocField",
   "field_name": "column_break_51",
   "idx": 0,
   "is_system_generated": 0,
   "modified": "2022-09-28 14:29:51.197203",
   "modified_by": "Administrator",
   "module": null,
   "name": "Delivery Note-column_break_51-hidden",
   "owner": "Administrator",
   "property": "hidden",
   "property_type": "Check",
   "row_name": null,
   "value": "1"
  },
  {
   "_assign": null,
   "_comments": null,
   "_liked_by": null,
   "_user_tags": null,
   "creation": "2022-09-28 14:29:51.108788",
   "default_value": null,
   "doc_type": "Delivery Note",
   "docstatus": 0,
   "doctype_or_field": "DocField",
   "field_name": "base_discount_amount",
   "idx": 0,
   "is_system_generated": 0,
   "modified": "2022-09-28 14:29:51.108788",
   "modified_by": "Administrator",
   "module": null,
   "name": "Delivery Note-base_discount_amount-hidden",
   "owner": "Administrator",
   "property": "hidden",
   "property_type": "Check",
   "row_name": null,
   "value": "1"
  },
  {
   "_assign": null,
   "_comments": null,
   "_liked_by": null,
   "_user_tags": null,
   "creation": "2022-09-28 14:29:51.012057",
   "default_value": null,
   "doc_type": "Delivery Note",
   "docstatus": 0,
   "doctype_or_field": "DocField",
   "field_name": "apply_discount_on",
   "idx": 0,
   "is_system_generated": 0,
   "modified": "2022-09-28 14:29:51.012057",
   "modified_by": "Administrator",
   "module": null,
   "name": "Delivery Note-apply_discount_on-hidden",
   "owner": "Administrator",
   "property": "hidden",
   "property_type": "Check",
   "row_name": null,
   "value": "1"
  },
  {
   "_assign": null,
   "_comments": null,
   "_liked_by": null,
   "_user_tags": null,
   "creation": "2022-09-28 14:29:50.887186",
   "default_value": null,
   "doc_type": "Delivery Note",
   "docstatus": 0,
   "doctype_or_field": "DocField",
   "field_name": "section_break_49",
   "idx": 0,
   "is_system_generated": 0,
   "modified": "2022-09-28 14:29:50.887186",
   "modified_by": "Administrator",
   "module": null,
   "name": "Delivery Note-section_break_49-hidden",
   "owner": "Administrator",
   "property": "hidden",
   "property_type": "Check",
   "row_name": null,
   "value": "1"
  },
  {
   "_assign": null,
   "_comments": null,
   "_liked_by": null,
   "_user_tags": null,
   "creation": "2022-09-28 14:27:58.757868",
   "default_value": null,
   "doc_type": "Delivery Note",
   "docstatus": 0,
   "doctype_or_field": "DocField",
   "field_name": "apply_discount_on",
   "idx": 0,
   "is_system_generated": 0,
   "modified": "2022-09-28 14:27:58.757868",
   "modified_by": "Administrator",
   "module": null,
   "name": "Delivery Note-apply_discount_on-default",
   "owner": "Administrator",
   "property": "default",
   "property_type": "Text",
   "row_name": null,
   "value": "Net Total"
  },
  {
   "_assign": null,
   "_comments": null,
   "_liked_by": null,
   "_user_tags": null,
   "creation": "2022-09-28 14:27:58.668492",
   "default_value": null,
   "doc_type": "Delivery Note",
   "docstatus": 0,
   "doctype_or_field": "DocField",
   "field_name": "set_target_warehouse",
   "idx": 0,
   "is_system_generated": 0,
   "modified": "2022-09-28 14:27:58.668492",
   "modified_by": "Administrator",
   "module": null,
   "name": "Delivery Note-set_target_warehouse-hidden",
   "owner": "Administrator",
   "property": "hidden",
   "property_type": "Check",
   "row_name": null,
   "value": "1"
  },
  {
   "_assign": null,
   "_comments": null,
   "_liked_by": null,
   "_user_tags": null,
   "creation": "2022-09-28 14:27:58.581398",
   "default_value": null,
   "doc_type": "Delivery Note",
   "docstatus": 0,
   "doctype_or_field": "DocField",
   "field_name": "col_break_warehouse",
   "idx": 0,
   "is_system_generated": 0,
   "modified": "2022-09-28 14:27:58.581398",
   "modified_by": "Administrator",
   "module": null,
   "name": "Delivery Note-col_break_warehouse-hidden",
   "owner": "Administrator",
   "property": "hidden",
   "property_type": "Check",
   "row_name": null,
   "value": "1"
  },
  {
   "_assign": null,
   "_comments": null,
   "_liked_by": null,
   "_user_tags": null,
   "creation": "2022-09-28 14:27:58.493344",
   "default_value": null,
   "doc_type": "Delivery Note",
   "docstatus": 0,
   "doctype_or_field": "DocField",
   "field_name": "set_warehouse",
   "idx": 0,
   "is_system_generated": 0,
   "modified": "2022-09-28 14:27:58.493344",
   "modified_by": "Administrator",
   "module": null,
   "name": "Delivery Note-set_warehouse-hidden",
   "owner": "Administrator",
   "property": "hidden",
   "property_type": "Check",
   "row_name": null,
   "value": "1"
  },
  {
   "_assign": null,
   "_comments": null,
   "_liked_by": null,
   "_user_tags": null,
   "creation": "2022-09-28 14:27:58.280519",
   "default_value": null,
   "doc_type": "Delivery Note",
   "docstatus": 0,
   "doctype_or_field": "DocField",
   "field_name": "sec_warehouse",
   "idx": 0,
   "is_system_generated": 0,
   "modified": "2022-09-28 14:27:58.280519",
   "modified_by": "Administrator",
   "module": null,
   "name": "Delivery Note-sec_warehouse-hidden",
   "owner": "Administrator",
   "property": "hidden",
   "property_type": "Check",
   "row_name": null,
   "value": "1"
  },
  {
   "_assign": null,
   "_comments": null,
   "_liked_by": null,
   "_user_tags": null,
   "creation": "2022-09-28 14:27:58.187941",
   "default_value": null,
   "doc_type": "Delivery Note",
   "docstatus": 0,
   "doctype_or_field": "DocField",
   "field_name": "ignore_pricing_rule",
   "idx": 0,
   "is_system_generated": 0,
   "modified": "2022-09-28 14:27:58.187941",
   "modified_by": "Administrator",
   "module": null,
   "name": "Delivery Note-ignore_pricing_rule-hidden",
   "owner": "Administrator",
   "property": "hidden",
   "property_type": "Check",
   "row_name": null,
   "value": "1"
  },
  {
   "_assign": null,
   "_comments": null,
   "_liked_by": null,
   "_user_tags": null,
   "creation": "2022-09-28 14:27:58.099459",
   "default_value": null,
   "doc_type": "Delivery Note",
   "docstatus": 0,
   "doctype_or_field": "DocField",
   "field_name": "col_break23",
   "idx": 0,
   "is_system_generated": 0,
   "modified": "2022-09-28 14:27:58.099459",
   "modified_by": "Administrator",
   "module": null,
   "name": "Delivery Note-col_break23-hidden",
   "owner": "Administrator",
   "property": "hidden",
   "property_type": "Check",
   "row_name": null,
   "value": "1"
  },
  {
   "_assign": null,
   "_comments": null,
   "_liked_by": null,
   "_user_tags": null,
   "creation": "2022-09-28 14:27:58.010394",
   "default_value": null,
   "doc_type": "Delivery Note",
   "docstatus": 0,
   "doctype_or_field": "DocField",
   "field_name": "currency_and_price_list",
   "idx": 0,
   "is_system_generated": 0,
   "modified": "2022-09-28 14:27:58.010394",
   "modified_by": "Administrator",
   "module": null,
   "name": "Delivery Note-currency_and_price_list-hidden",
   "owner": "Administrator",
   "property": "hidden",
   "property_type": "Check",
   "row_name": null,
   "value": "1"
  },
  {
   "_assign": null,
   "_comments": null,
   "_liked_by": null,
   "_user_tags": null,
   "creation": "2022-09-28 14:27:57.925661",
   "default_value": null,
   "doc_type": "Delivery Note",
   "docstatus": 0,
   "doctype_or_field": "DocField",
   "field_name": "section_break_18",
   "idx": 0,
   "is_system_generated": 0,
   "modified": "2022-09-28 14:27:57.925661",
   "modified_by": "Administrator",
   "module": null,
   "name": "Delivery Note-section_break_18-hidden",
   "owner": "Administrator",
   "property": "hidden",
   "property_type": "Check",
   "row_name": null,
   "value": "1"
  },
  {
   "_assign": null,
   "_comments": null,
   "_liked_by": null,
   "_user_tags": null,
   "creation": "2022-09-28 14:27:57.835783",
   "default_value": null,
   "doc_type": "Delivery Note",
   "docstatus": 0,
   "doctype_or_field": "DocField",
   "field_name": "po_date",
   "idx": 0,
   "is_system_generated": 0,
   "modified": "2022-09-28 14:27:57.835783",
   "modified_by": "Administrator",
   "module": null,
   "name": "Delivery Note-po_date-hidden",
   "owner": "Administrator",
   "property": "hidden",
   "property_type": "Check",
   "row_name": null,
   "value": "1"
  },
  {
   "_assign": null,
   "_comments": null,
   "_liked_by": null,
   "_user_tags": null,
   "creation": "2022-09-28 14:27:57.748278",
   "default_value": null,
   "doc_type": "Delivery Note",
   "docstatus": 0,
   "doctype_or_field": "DocField",
   "field_name": "column_break_17",
   "idx": 0,
   "is_system_generated": 0,
   "modified": "2022-09-28 14:27:57.748278",
   "modified_by": "Administrator",
   "module": null,
   "name": "Delivery Note-column_break_17-hidden",
   "owner": "Administrator",
   "property": "hidden",
   "property_type": "Check",
   "row_name": null,
   "value": "1"
  },
  {
   "_assign": null,
   "_comments": null,
   "_liked_by": null,
   "_user_tags": null,
   "creation": "2022-09-28 14:27:57.663313",
   "default_value": null,
   "doc_type": "Delivery Note",
   "docstatus": 0,
   "doctype_or_field": "DocField",
   "field_name": "po_no",
   "idx": 0,
   "is_system_generated": 0,
   "modified": "2022-09-28 14:27:57.663313",
   "modified_by": "Administrator",
   "module": null,
   "name": "Delivery Note-po_no-hidden",
   "owner": "Administrator",
   "property": "hidden",
   "property_type": "Check",
   "row_name": null,
   "value": "1"
  },
  {
   "_assign": null,
   "_comments": null,
   "_liked_by": null,
   "_user_tags": null,
   "creation": "2022-09-28 14:27:57.579309",
   "default_value": null,
   "doc_type": "Delivery Note",
   "docstatus": 0,
   "doctype_or_field": "DocField",
   "field_name": "customer_po_details",
   "idx": 0,
   "is_system_generated": 0,
   "modified": "2022-09-28 14:27:57.579309",
   "modified_by": "Administrator",
   "module": null,
   "name": "Delivery Note-customer_po_details-hidden",
   "owner": "Administrator",
   "property": "hidden",
   "property_type": "Check",
   "row_name": null,
   "value": "1"
  },
  {
   "_assign": null,
   "_comments": null,
   "_liked_by": null,
   "_user_tags": null,
   "creation": "2022-09-28 14:27:57.494327",
   "default_value": null,
   "doc_type": "Delivery Note",
   "docstatus": 0,
   "doctype_or_field": "DocField",
   "field_name": "project",
   "idx": 0,
   "is_system_generated": 0,
   "modified": "2022-09-28 14:27:57.494327",
   "modified_by": "Administrator",
   "module": null,
   "name": "Delivery Note-project-hidden",
   "owner": "Administrator",
   "property": "hidden",
   "property_type": "Check",
   "row_name": null,
   "value": "1"
  },
  {
   "_assign": null,
   "_comments": null,
   "_liked_by": null,
   "_user_tags": null,
   "creation": "2022-09-28 14:27:57.403203",
   "default_value": null,
   "doc_type": "Delivery Note",
   "docstatus": 0,
   "doctype_or_field": "DocField",
   "field_name": "dimension_col_break",
   "idx": 0,
   "is_system_generated": 0,
   "modified": "2022-09-28 14:27:57.403203",
   "modified_by": "Administrator",
   "module": null,
   "name": "Delivery Note-dimension_col_break-hidden",
   "owner": "Administrator",
   "property": "hidden",
   "property_type": "Check",
   "row_name": null,
   "value": "1"
  },
  {
   "_assign": null,
   "_comments": null,
   "_liked_by": null,
   "_user_tags": null,
   "creation": "2022-09-28 14:27:57.314287",
   "default_value": null,
   "doc_type": "Delivery Note",
   "docstatus": 0,
   "doctype_or_field": "DocField",
   "field_name": "cost_center",
   "idx": 0,
   "is_system_generated": 0,
   "modified": "2022-09-28 14:27:57.314287",
   "modified_by": "Administrator",
   "module": null,
   "name": "Delivery Note-cost_center-hidden",
   "owner": "Administrator",
   "property": "hidden",
   "property_type": "Check",
   "row_name": null,
   "value": "1"
  },
  {
   "_assign": null,
   "_comments": null,
   "_liked_by": null,
   "_user_tags": null,
   "creation": "2022-09-28 14:27:57.226711",
   "default_value": null,
   "doc_type": "Delivery Note",
   "docstatus": 0,
   "doctype_or_field": "DocField",
   "field_name": "accounting_dimensions_section",
   "idx": 0,
   "is_system_generated": 0,
   "modified": "2022-09-28 14:27:57.226711",
   "modified_by": "Administrator",
   "module": null,
   "name": "Delivery Note-accounting_dimensions_section-hidden",
   "owner": "Administrator",
   "property": "hidden",
   "property_type": "Check",
   "row_name": null,
   "value": "1"
  },
  {
   "_assign": null,
   "_comments": null,
   "_liked_by": null,
   "_user_tags": null,
   "creation": "2022-09-22 17:30:48.286267",
   "default_value": null,
   "doc_type": "Delivery Note",
   "docstatus": 0,
   "doctype_or_field": "DocField",
   "field_name": "scan_barcode",
   "idx": 0,
   "is_system_generated": 1,
   "modified": "2022-09-22 17:30:48.286267",
   "modified_by": "Administrator",
   "module": null,
   "name": "Delivery Note-scan_barcode-hidden",
   "owner": "Administrator",
   "property": "hidden",
   "property_type": "Check",
   "row_name": null,
   "value": "0"
  },
  {
   "_assign": null,
   "_comments": null,
   "_liked_by": null,
   "_user_tags": null,
   "creation": "2022-09-22 17:30:46.649570",
   "default_value": null,
   "doc_type": "Delivery Note",
   "docstatus": 0,
   "doctype_or_field": "DocField",
   "field_name": "in_words",
   "idx": 0,
   "is_system_generated": 0,
   "modified": "2022-09-22 17:30:46.649570",
   "modified_by": "Administrator",
   "module": null,
   "name": "Delivery Note-in_words-print_hide",
   "owner": "Administrator",
   "property": "print_hide",
   "property_type": "Check",
   "row_name": null,
   "value": "0"
  },
  {
   "_assign": null,
   "_comments": null,
   "_liked_by": null,
   "_user_tags": null,
   "creation": "2022-09-22 17:30:46.641637",
   "default_value": null,
   "doc_type": "Delivery Note",
   "docstatus": 0,
   "doctype_or_field": "DocField",
   "field_name": "in_words",
   "idx": 0,
   "is_system_generated": 0,
   "modified": "2022-09-22 17:30:46.641637",
   "modified_by": "Administrator",
   "module": null,
   "name": "Delivery Note-in_words-hidden",
   "owner": "Administrator",
   "property": "hidden",
   "property_type": "Check",
   "row_name": null,
   "value": "0"
  },
  {
   "_assign": null,
   "_comments": null,
   "_liked_by": null,
   "_user_tags": null,
   "creation": "2022-09-22 17:30:46.365826",
   "default_value": null,
   "doc_type": "Delivery Note",
   "docstatus": 0,
   "doctype_or_field": "DocField",
   "field_name": "disable_rounded_total",
   "idx": 0,
   "is_system_generated": 0,
   "modified": "2022-09-22 17:30:46.365826",
   "modified_by": "Administrator",
   "module": null,
   "name": "Delivery Note-disable_rounded_total-default",
   "owner": "Administrator",
   "property": "default",
   "property_type": "Text",
   "row_name": null,
   "value": "0"
  },
  {
   "_assign": null,
   "_comments": null,
   "_liked_by": null,
   "_user_tags": null,
   "creation": "2022-09-22 17:30:46.356437",
   "default_value": null,
   "doc_type": "Delivery Note",
   "docstatus": 0,
   "doctype_or_field": "DocField",
   "field_name": "rounded_total",
   "idx": 0,
   "is_system_generated": 0,
   "modified": "2022-09-22 17:30:46.356437",
   "modified_by": "Administrator",
   "module": null,
   "name": "Delivery Note-rounded_total-print_hide",
   "owner": "Administrator",
   "property": "print_hide",
   "property_type": "Check",
   "row_name": null,
   "value": "0"
  },
  {
   "_assign": null,
   "_comments": null,
   "_liked_by": null,
   "_user_tags": null,
   "creation": "2022-09-22 17:30:46.344862",
   "default_value": null,
   "doc_type": "Delivery Note",
   "docstatus": 0,
   "doctype_or_field": "DocField",
   "field_name": "rounded_total",
   "idx": 0,
   "is_system_generated": 0,
   "modified": "2022-09-22 17:30:46.344862",
   "modified_by": "Administrator",
   "module": null,
   "name": "Delivery Note-rounded_total-hidden",
   "owner": "Administrator",
   "property": "hidden",
   "property_type": "Check",
   "row_name": null,
   "value": "0"
  },
  {
   "_assign": null,
   "_comments": null,
   "_liked_by": null,
   "_user_tags": null,
   "creation": "2022-09-22 17:30:46.335084",
   "default_value": null,
   "doc_type": "Delivery Note",
   "docstatus": 0,
   "doctype_or_field": "DocField",
   "field_name": "base_rounded_total",
   "idx": 0,
   "is_system_generated": 0,
   "modified": "2022-09-22 17:30:46.335084",
   "modified_by": "Administrator",
   "module": null,
   "name": "Delivery Note-base_rounded_total-print_hide",
   "owner": "Administrator",
   "property": "print_hide",
   "property_type": "Check",
   "row_name": null,
   "value": "1"
  },
  {
   "_assign": null,
   "_comments": null,
   "_liked_by": null,
   "_user_tags": null,
   "creation": "2022-09-22 17:30:46.323873",
   "default_value": null,
   "doc_type": "Delivery Note",
   "docstatus": 0,
   "doctype_or_field": "DocField",
   "field_name": "base_rounded_total",
   "idx": 0,
   "is_system_generated": 0,
   "modified": "2022-09-22 17:30:46.323873",
   "modified_by": "Administrator",
   "module": null,
   "name": "Delivery Note-base_rounded_total-hidden",
   "owner": "Administrator",
   "property": "hidden",
   "property_type": "Check",
   "row_name": null,
   "value": "0"
  },
  {
   "_assign": null,
   "_comments": null,
   "_liked_by": null,
   "_user_tags": null,
   "creation": "2022-09-22 17:30:43.593963",
   "default_value": null,
   "doc_type": "Delivery Note",
   "docstatus": 0,
   "doctype_or_field": "DocField",
   "field_name": "tax_id",
   "idx": 0,
   "is_system_generated": 0,
   "modified": "2022-09-22 17:30:43.593963",
   "modified_by": "Administrator",
   "module": null,
   "name": "Delivery Note-tax_id-print_hide",
   "owner": "Administrator",
   "property": "print_hide",
   "property_type": "Check",
   "row_name": null,
   "value": "0"
  },
  {
   "_assign": null,
   "_comments": null,
   "_liked_by": null,
   "_user_tags": null,
   "creation": "2022-09-22 17:30:43.582117",
   "default_value": null,
   "doc_type": "Delivery Note",
   "docstatus": 0,
   "doctype_or_field": "DocField",
   "field_name": "tax_id",
   "idx": 0,
   "is_system_generated": 0,
   "modified": "2022-09-22 17:30:43.582117",
   "modified_by": "Administrator",
   "module": null,
   "name": "Delivery Note-tax_id-hidden",
   "owner": "Administrator",
   "property": "hidden",
   "property_type": "Check",
   "row_name": null,
   "value": "0"
  }
 ],
 "sync_on_migrate": 1
}